lakota/__init__.py
lakota/__main__.py
lakota/batch.py
lakota/changelog.py
lakota/cli.py
lakota/collection.py
lakota/commit.py
lakota/frame.py
lakota/http_pod.py
lakota/pod.py
lakota/repo.py
lakota/s3_pod.py
lakota/schema.py
lakota/series.py
lakota/server.py
lakota/sexpr.py
lakota/utils.py
lakota-0.6.8.dist-info/METADATA
lakota-0.6.8.dist-info/WHEEL
lakota-0.6.8.dist-info/entry_points.txt
lakota-0.6.8.dist-info/top_level.txt
lakota-0.6.8.dist-info/RECORD
