Metadata-Version: 2.1
Name: lakota
Version: 0.6.8
Summary: Versioned columnar storage for timeseries
Home-page: https://github.com/bertrandchenal/lakota
Author: Bertrand Chenal
License: MIT
Requires-Dist: msgpack
Requires-Dist: numcodecs
Requires-Dist: numpy
Requires-Dist: pytz
Requires-Dist: tabulate
